{
  "summary": {
    "mission": "Farm the nearest useful resource safely.",
    "autonomy_level": 1,
    "started": "2026-04-18T03:48:19",
    "ended": "2026-04-18T04:00:51",
    "duration_seconds": 751.5,
    "duration_text": "12m 31s",
    "total_actions": 4,
    "approvals": 0,
    "rejections": 0,
    "corrections": 0,
    "memory_hits": 0,
    "api_calls": 4,
    "errors": 0,
    "captchas": 0,
    "timings": 59
  },
  "events": [
    {
      "timestamp": "2026-04-18T03:48:19",
      "elapsed_seconds": 0.0,
      "event_type": "info",
      "action_type": "",
      "label": "",
      "target_id": "",
      "outcome": "",
      "detail": "Session started: Farm the nearest useful resource safely."
    },
    {
      "timestamp": "2026-04-18T03:48:20",
      "elapsed_seconds": 0.6,
      "event_type": "timing",
      "action_type": "",
      "label": "",
      "target_id": "",
      "outcome": "observed",
      "detail": "title=Rise of Kingdoms",
      "stage": "window_capture",
      "duration_ms": 51.07
    },
    {
      "timestamp": "2026-04-18T03:48:20",
      "elapsed_seconds": 0.6,
      "event_type": "timing",
      "action_type": "",
      "label": "",
      "target_id": "",
      "outcome": "observed",
      "detail": "detections=0",
      "stage": "yolo_detect",
      "duration_ms": 0.02
    },
    {
      "timestamp": "2026-04-18T03:48:29",
      "elapsed_seconds": 10.0,
      "event_type": "timing",
      "action_type": "",
      "label": "",
      "target_id": "",
      "outcome": "observed",
      "detail": "regions=25",
      "stage": "ocr_regions",
      "duration_ms": 1591.59
    },
    {
      "timestamp": "2026-04-18T03:48:30",
      "elapsed_seconds": 11.3,
      "event_type": "timing",
      "action_type": "",
      "label": "",
      "target_id": "",
      "outcome": "observed",
      "detail": "keys=0",
      "stage": "resource_context",
      "duration_ms": 1250.63
    },
    {
      "timestamp": "2026-04-18T03:48:30",
      "elapsed_seconds": 11.3,
      "event_type": "timing",
      "action_type": "",
      "label": "",
      "target_id": "",
      "outcome": "observed",
      "detail": "miss",
      "stage": "planner_memory_lookup",
      "duration_ms": 0.01
    },
    {
      "timestamp": "2026-04-18T03:48:34",
      "elapsed_seconds": 14.7,
      "event_type": "timing",
      "action_type": "",
      "label": "",
      "target_id": "",
      "outcome": "observed",
      "detail": "action=wait",
      "stage": "planner_request",
      "duration_ms": 3456.99
    },
    {
      "timestamp": "2026-04-18T03:48:47",
      "elapsed_seconds": 27.6,
      "event_type": "action",
      "action_type": "wait",
      "label": "Observe current world map state",
      "target_id": "",
      "outcome": "success",
      "detail": ""
    },
    {
      "timestamp": "2026-04-18T03:48:48",
      "elapsed_seconds": 29.1,
      "event_type": "timing",
      "action_type": "",
      "label": "",
      "target_id": "",
      "outcome": "observed",
      "detail": "result=True",
      "stage": "planner_wait",
      "duration_ms": 1489.92
    },
    {
      "timestamp": "2026-04-18T03:48:49",
      "elapsed_seconds": 29.7,
      "event_type": "timing",
      "action_type": "",
      "label": "",
      "target_id": "",
      "outcome": "observed",
      "detail": "title=Rise of Kingdoms",
      "stage": "window_capture",
      "duration_ms": 56.8
    },
    {
      "timestamp": "2026-04-18T03:48:49",
      "elapsed_seconds": 29.7,
      "event_type": "timing",
      "action_type": "",
      "label": "",
      "target_id": "",
      "outcome": "observed",
      "detail": "detections=0",
      "stage": "yolo_detect",
      "duration_ms": 0.03
    },
    {
      "timestamp": "2026-04-18T03:48:52",
      "elapsed_seconds": 32.5,
      "event_type": "timing",
      "action_type": "",
      "label": "",
      "target_id": "",
      "outcome": "observed",
      "detail": "regions=27",
      "stage": "ocr_regions",
      "duration_ms": 2463.96
    },
    {
      "timestamp": "2026-04-18T03:48:53",
      "elapsed_seconds": 33.6,
      "event_type": "timing",
      "action_type": "",
      "label": "",
      "target_id": "",
      "outcome": "observed",
      "detail": "keys=0",
      "stage": "resource_context",
      "duration_ms": 1100.7
    },
    {
      "timestamp": "2026-04-18T03:48:53",
      "elapsed_seconds": 33.6,
      "event_type": "timing",
      "action_type": "",
      "label": "",
      "target_id": "",
      "outcome": "observed",
      "detail": "miss",
      "stage": "planner_memory_lookup",
      "duration_ms": 0.12
    },
    {
      "timestamp": "2026-04-18T03:48:56",
      "elapsed_seconds": 36.6,
      "event_type": "timing",
      "action_type": "",
      "label": "",
      "target_id": "",
      "outcome": "observed",
      "detail": "action=wait",
      "stage": "planner_request",
      "duration_ms": 3031.44
    },
    {
      "timestamp": "2026-04-18T03:48:56",
      "elapsed_seconds": 36.6,
      "event_type": "action",
      "action_type": "wait",
      "label": "re-observe",
      "target_id": "",
      "outcome": "success",
      "detail": ""
    },
    {
      "timestamp": "2026-04-18T03:48:57",
      "elapsed_seconds": 37.6,
      "event_type": "timing",
      "action_type": "",
      "label": "",
      "target_id": "",
      "outcome": "observed",
      "detail": "result=True",
      "stage": "planner_wait",
      "duration_ms": 999.07
    },
    {
      "timestamp": "2026-04-18T03:48:57",
      "elapsed_seconds": 38.1,
      "event_type": "timing",
      "action_type": "",
      "label": "",
      "target_id": "",
      "outcome": "observed",
      "detail": "title=Rise of Kingdoms",
      "stage": "window_capture",
      "duration_ms": 39.88
    },
    {
      "timestamp": "2026-04-18T03:48:57",
      "elapsed_seconds": 38.1,
      "event_type": "timing",
      "action_type": "",
      "label": "",
      "target_id": "",
      "outcome": "observed",
      "detail": "detections=0",
      "stage": "yolo_detect",
      "duration_ms": 0.01
    },
    {
      "timestamp": "2026-04-18T03:49:00",
      "elapsed_seconds": 41.0,
      "event_type": "timing",
      "action_type": "",
      "label": "",
      "target_id": "",
      "outcome": "observed",
      "detail": "regions=35",
      "stage": "ocr_regions",
      "duration_ms": 2388.82
    },
    {
      "timestamp": "2026-04-18T03:49:02",
      "elapsed_seconds": 42.5,
      "event_type": "timing",
      "action_type": "",
      "label": "",
      "target_id": "",
      "outcome": "observed",
      "detail": "keys=0",
      "stage": "resource_context",
      "duration_ms": 1474.09
    },
    {
      "timestamp": "2026-04-18T03:49:02",
      "elapsed_seconds": 42.5,
      "event_type": "timing",
      "action_type": "",
      "label": "",
      "target_id": "",
      "outcome": "observed",
      "detail": "miss",
      "stage": "planner_memory_lookup",
      "duration_ms": 0.0
    },
    {
      "timestamp": "2026-04-18T03:49:04",
      "elapsed_seconds": 44.8,
      "event_type": "timing",
      "action_type": "",
      "label": "",
      "target_id": "",
      "outcome": "observed",
      "detail": "action=wait",
      "stage": "planner_request",
      "duration_ms": 2322.76
    },
    {
      "timestamp": "2026-04-18T03:49:04",
      "elapsed_seconds": 44.8,
      "event_type": "action",
      "action_type": "wait",
      "label": "observe world map state",
      "target_id": "",
      "outcome": "success",
      "detail": ""
    },
    {
      "timestamp": "2026-04-18T03:49:05",
      "elapsed_seconds": 46.3,
      "event_type": "timing",
      "action_type": "",
      "label": "",
      "target_id": "",
      "outcome": "observed",
      "detail": "result=True",
      "stage": "planner_wait",
      "duration_ms": 1475.48
    },
    {
      "timestamp": "2026-04-18T03:49:06",
      "elapsed_seconds": 46.8,
      "event_type": "timing",
      "action_type": "",
      "label": "",
      "target_id": "",
      "outcome": "observed",
      "detail": "title=Rise of Kingdoms",
      "stage": "window_capture",
      "duration_ms": 43.86
    },
    {
      "timestamp": "2026-04-18T03:49:06",
      "elapsed_seconds": 46.8,
      "event_type": "timing",
      "action_type": "",
      "label": "",
      "target_id": "",
      "outcome": "observed",
      "detail": "detections=0",
      "stage": "yolo_detect",
      "duration_ms": 0.01
    },
    {
      "timestamp": "2026-04-18T03:49:10",
      "elapsed_seconds": 50.9,
      "event_type": "timing",
      "action_type": "",
      "label": "",
      "target_id": "",
      "outcome": "observed",
      "detail": "regions=33",
      "stage": "ocr_regions",
      "duration_ms": 3050.51
    },
    {
      "timestamp": "2026-04-18T03:49:12",
      "elapsed_seconds": 52.7,
      "event_type": "timing",
      "action_type": "",
      "label": "",
      "target_id": "",
      "outcome": "observed",
      "detail": "keys=0",
      "stage": "resource_context",
      "duration_ms": 1804.94
    },
    {
      "timestamp": "2026-04-18T03:49:12",
      "elapsed_seconds": 52.7,
      "event_type": "timing",
      "action_type": "",
      "label": "",
      "target_id": "",
      "outcome": "observed",
      "detail": "miss",
      "stage": "planner_memory_lookup",
      "duration_ms": 0.01
    },
    {
      "timestamp": "2026-04-18T03:49:15",
      "elapsed_seconds": 56.2,
      "event_type": "timing",
      "action_type": "",
      "label": "",
      "target_id": "",
      "outcome": "observed",
      "detail": "action=wait",
      "stage": "planner_request",
      "duration_ms": 3574.16
    },
    {
      "timestamp": "2026-04-18T03:49:15",
      "elapsed_seconds": 56.2,
      "event_type": "action",
      "action_type": "wait",
      "label": "wait for UI to settle",
      "target_id": "",
      "outcome": "success",
      "detail": ""
    },
    {
      "timestamp": "2026-04-18T03:49:17",
      "elapsed_seconds": 57.7,
      "event_type": "timing",
      "action_type": "",
      "label": "",
      "target_id": "",
      "outcome": "observed",
      "detail": "result=True",
      "stage": "planner_wait",
      "duration_ms": 1428.23
    },
    {
      "timestamp": "2026-04-18T03:49:17",
      "elapsed_seconds": 58.2,
      "event_type": "timing",
      "action_type": "",
      "label": "",
      "target_id": "",
      "outcome": "observed",
      "detail": "title=Rise of Kingdoms",
      "stage": "window_capture",
      "duration_ms": 41.2
    },
    {
      "timestamp": "2026-04-18T03:49:17",
      "elapsed_seconds": 58.2,
      "event_type": "timing",
      "action_type": "",
      "label": "",
      "target_id": "",
      "outcome": "observed",
      "detail": "detections=0",
      "stage": "yolo_detect",
      "duration_ms": 0.0
    },
    {
      "timestamp": "2026-04-18T03:49:22",
      "elapsed_seconds": 62.4,
      "event_type": "timing",
      "action_type": "",
      "label": "",
      "target_id": "",
      "outcome": "observed",
      "detail": "regions=40",
      "stage": "ocr_regions",
      "duration_ms": 2973.27
    },
    {
      "timestamp": "2026-04-18T03:49:23",
      "elapsed_seconds": 63.7,
      "event_type": "timing",
      "action_type": "",
      "label": "",
      "target_id": "",
      "outcome": "observed",
      "detail": "keys=0",
      "stage": "resource_context",
      "duration_ms": 1275.94
    },
    {
      "timestamp": "2026-04-18T03:49:23",
      "elapsed_seconds": 63.7,
      "event_type": "timing",
      "action_type": "",
      "label": "",
      "target_id": "",
      "outcome": "observed",
      "detail": "miss",
      "stage": "planner_memory_lookup",
      "duration_ms": 0.01
    },
    {
      "timestamp": "2026-04-18T03:49:25",
      "elapsed_seconds": 66.2,
      "event_type": "timing",
      "action_type": "",
      "label": "",
      "target_id": "",
      "outcome": "observed",
      "detail": "action=click",
      "stage": "planner_request",
      "duration_ms": 2562.28
    },
    {
      "timestamp": "2026-04-18T03:49:35",
      "elapsed_seconds": 76.0,
      "event_type": "timing",
      "action_type": "",
      "label": "",
      "target_id": "",
      "outcome": "observed",
      "detail": "title=Rise of Kingdoms",
      "stage": "window_capture",
      "duration_ms": 45.97
    },
    {
      "timestamp": "2026-04-18T03:49:35",
      "elapsed_seconds": 76.0,
      "event_type": "timing",
      "action_type": "",
      "label": "",
      "target_id": "",
      "outcome": "observed",
      "detail": "detections=0",
      "stage": "yolo_detect",
      "duration_ms": 0.01
    },
    {
      "timestamp": "2026-04-18T03:49:38",
      "elapsed_seconds": 79.1,
      "event_type": "timing",
      "action_type": "",
      "label": "",
      "target_id": "",
      "outcome": "observed",
      "detail": "regions=32",
      "stage": "ocr_regions",
      "duration_ms": 2833.01
    },
    {
      "timestamp": "2026-04-18T03:49:40",
      "elapsed_seconds": 80.5,
      "event_type": "timing",
      "action_type": "",
      "label": "",
      "target_id": "",
      "outcome": "observed",
      "detail": "keys=0",
      "stage": "resource_context",
      "duration_ms": 1318.23
    },
    {
      "timestamp": "2026-04-18T03:49:40",
      "elapsed_seconds": 80.5,
      "event_type": "timing",
      "action_type": "",
      "label": "",
      "target_id": "",
      "outcome": "observed",
      "detail": "miss",
      "stage": "planner_memory_lookup",
      "duration_ms": 0.02
    },
    {
      "timestamp": "2026-04-18T03:49:42",
      "elapsed_seconds": 83.0,
      "event_type": "timing",
      "action_type": "",
      "label": "",
      "target_id": "",
      "outcome": "observed",
      "detail": "action=click",
      "stage": "planner_request",
      "duration_ms": 2562.85
    },
    {
      "timestamp": "2026-04-18T03:49:44",
      "elapsed_seconds": 84.7,
      "event_type": "timing",
      "action_type": "",
      "label": "",
      "target_id": "",
      "outcome": "observed",
      "detail": "title=Rise of Kingdoms",
      "stage": "window_capture",
      "duration_ms": 44.53
    },
    {
      "timestamp": "2026-04-18T03:49:44",
      "elapsed_seconds": 84.7,
      "event_type": "timing",
      "action_type": "",
      "label": "",
      "target_id": "",
      "outcome": "observed",
      "detail": "detections=0",
      "stage": "yolo_detect",
      "duration_ms": 0.01
    },
    {
      "timestamp": "2026-04-18T03:49:47",
      "elapsed_seconds": 87.3,
      "event_type": "timing",
      "action_type": "",
      "label": "",
      "target_id": "",
      "outcome": "observed",
      "detail": "regions=39",
      "stage": "ocr_regions",
      "duration_ms": 2436.64
    },
    {
      "timestamp": "2026-04-18T03:49:48",
      "elapsed_seconds": 89.1,
      "event_type": "timing",
      "action_type": "",
      "label": "",
      "target_id": "",
      "outcome": "observed",
      "detail": "keys=0",
      "stage": "resource_context",
      "duration_ms": 1775.36
    },
    {
      "timestamp": "2026-04-18T03:49:48",
      "elapsed_seconds": 89.1,
      "event_type": "timing",
      "action_type": "",
      "label": "",
      "target_id": "",
      "outcome": "observed",
      "detail": "miss",
      "stage": "planner_memory_lookup",
      "duration_ms": 0.01
    },
    {
      "timestamp": "2026-04-18T03:49:51",
      "elapsed_seconds": 91.5,
      "event_type": "timing",
      "action_type": "",
      "label": "",
      "target_id": "",
      "outcome": "observed",
      "detail": "action=click",
      "stage": "planner_request",
      "duration_ms": 2390.23
    },
    {
      "timestamp": "2026-04-18T03:49:52",
      "elapsed_seconds": 92.5,
      "event_type": "timing",
      "action_type": "",
      "label": "",
      "target_id": "",
      "outcome": "observed",
      "detail": "title=Rise of Kingdoms",
      "stage": "window_capture",
      "duration_ms": 46.87
    },
    {
      "timestamp": "2026-04-18T03:49:52",
      "elapsed_seconds": 92.5,
      "event_type": "timing",
      "action_type": "",
      "label": "",
      "target_id": "",
      "outcome": "observed",
      "detail": "detections=0",
      "stage": "yolo_detect",
      "duration_ms": 0.01
    },
    {
      "timestamp": "2026-04-18T03:49:54",
      "elapsed_seconds": 94.8,
      "event_type": "timing",
      "action_type": "",
      "label": "",
      "target_id": "",
      "outcome": "observed",
      "detail": "regions=36",
      "stage": "ocr_regions",
      "duration_ms": 2031.07
    },
    {
      "timestamp": "2026-04-18T03:49:56",
      "elapsed_seconds": 96.7,
      "event_type": "timing",
      "action_type": "",
      "label": "",
      "target_id": "",
      "outcome": "observed",
      "detail": "keys=1",
      "stage": "resource_context",
      "duration_ms": 1978.86
    },
    {
      "timestamp": "2026-04-18T03:49:56",
      "elapsed_seconds": 96.7,
      "event_type": "timing",
      "action_type": "",
      "label": "",
      "target_id": "",
      "outcome": "observed",
      "detail": "miss",
      "stage": "planner_memory_lookup",
      "duration_ms": 0.01
    },
    {
      "timestamp": "2026-04-18T03:49:59",
      "elapsed_seconds": 99.4,
      "event_type": "timing",
      "action_type": "",
      "label": "",
      "target_id": "",
      "outcome": "observed",
      "detail": "action=click",
      "stage": "planner_request",
      "duration_ms": 2672.59
    },
    {
      "timestamp": "2026-04-18T03:50:00",
      "elapsed_seconds": 100.9,
      "event_type": "timing",
      "action_type": "",
      "label": "",
      "target_id": "",
      "outcome": "observed",
      "detail": "title=Rise of Kingdoms",
      "stage": "window_capture",
      "duration_ms": 52.91
    },
    {
      "timestamp": "2026-04-18T03:50:00",
      "elapsed_seconds": 100.9,
      "event_type": "timing",
      "action_type": "",
      "label": "",
      "target_id": "",
      "outcome": "observed",
      "detail": "detections=0",
      "stage": "yolo_detect",
      "duration_ms": 0.01
    },
    {
      "timestamp": "2026-04-18T03:50:03",
      "elapsed_seconds": 103.4,
      "event_type": "timing",
      "action_type": "",
      "label": "",
      "target_id": "",
      "outcome": "observed",
      "detail": "regions=38",
      "stage": "ocr_regions",
      "duration_ms": 2146.34
    },
    {
      "timestamp": "2026-04-18T03:50:03",
      "elapsed_seconds": 104.1,
      "event_type": "timing",
      "action_type": "",
      "label": "",
      "target_id": "",
      "outcome": "observed",
      "detail": "keys=1",
      "stage": "resource_context",
      "duration_ms": 739.06
    },
    {
      "timestamp": "2026-04-18T03:50:03",
      "elapsed_seconds": 104.1,
      "event_type": "timing",
      "action_type": "",
      "label": "",
      "target_id": "",
      "outcome": "observed",
      "detail": "miss",
      "stage": "planner_memory_lookup",
      "duration_ms": 0.01
    },
    {
      "timestamp": "2026-04-18T03:50:06",
      "elapsed_seconds": 106.5,
      "event_type": "timing",
      "action_type": "",
      "label": "",
      "target_id": "",
      "outcome": "observed",
      "detail": "action=stop",
      "stage": "planner_request",
      "duration_ms": 2402.28
    },
    {
      "timestamp": "2026-04-18T03:50:06",
      "elapsed_seconds": 106.5,
      "event_type": "timing",
      "action_type": "",
      "label": "",
      "target_id": "",
      "outcome": "observed",
      "detail": "result=True",
      "stage": "planner_stop",
      "duration_ms": 0.12
    },
    {
      "timestamp": "2026-04-18T03:51:57",
      "elapsed_seconds": 217.7,
      "event_type": "info",
      "action_type": "",
      "label": "",
      "target_id": "",
      "outcome": "",
      "detail": "Session stopped."
    },
    {
      "timestamp": "2026-04-18T04:00:47",
      "elapsed_seconds": 747.3,
      "event_type": "info",
      "action_type": "",
      "label": "",
      "target_id": "",
      "outcome": "",
      "detail": "Session stopped."
    },
    {
      "timestamp": "2026-04-18T04:00:51",
      "elapsed_seconds": 751.5,
      "event_type": "info",
      "action_type": "",
      "label": "",
      "target_id": "",
      "outcome": "",
      "detail": "Session stopped."
    }
  ]
}
